fresco_template/__init__.py
fresco_template/chameleon.py
fresco_template/core.py
fresco_template/jinja2.py
fresco_template/kajiki.py
fresco_template/piglet.py
fresco_template-1.0.0.dist-info/DESCRIPTION.rst
fresco_template-1.0.0.dist-info/METADATA
fresco_template-1.0.0.dist-info/RECORD
fresco_template-1.0.0.dist-info/WHEEL
fresco_template-1.0.0.dist-info/metadata.json
fresco_template-1.0.0.dist-info/top_level.txt
